splotch/__init__.py
splotch/axis_func.py
splotch/base_func.py
splotch/colorbar.py
splotch/defaults.py
splotch/plots_1d.py
splotch/plots_2d.py
splotch/styles.py
splotch-0.6.9.3.dist-info/LICENSE
splotch-0.6.9.3.dist-info/METADATA
splotch-0.6.9.3.dist-info/WHEEL
splotch-0.6.9.3.dist-info/top_level.txt
splotch-0.6.9.3.dist-info/RECORD
